rankerNN2pmml/__init__.py
rankerNN2pmml-0.1.2.dist-info/LICENSE
rankerNN2pmml-0.1.2.dist-info/METADATA
rankerNN2pmml-0.1.2.dist-info/WHEEL
rankerNN2pmml-0.1.2.dist-info/top_level.txt
rankerNN2pmml-0.1.2.dist-info/RECORD
