Metadata-Version: 2.1
Name: rankerNN2pmml
Version: 0.1.2
Summary: Exporter of pairwise ranker with Neural Nets as underlying model into PMML.
Home-page: https://github.com/liyinxiao/rankerNN2pmml
Author: Yinxiao Li
Author-email: liyinxiao1227@gmail.com
License: UNKNOWN
Platform: UNKNOWN
Classifier: Programming Language :: Python :: 3
Classifier: License :: OSI Approved :: MIT License
Classifier: Operating System :: OS Independent
